dsind/__init__.py
dsind/feature_engineering.py
dsind-0.1.0.dist-info/WHEEL
dsind-0.1.0.dist-info/METADATA
dsind-0.1.0.dist-info/RECORD
